dbj.py
dbj-0.2.0.dist-info/METADATA
dbj-0.2.0.dist-info/WHEEL
dbj-0.2.0.dist-info/licenses/LICENSE
dbj-0.2.0.dist-info/RECORD
