Metadata-Version: 2.3
Name: dbj
Version: 0.2.0
Summary: Simple embedded in memory json database
Project-URL: Homepage, https://github.com/pdrb/dbj
Author-email: Pedro Gonring <pedro@bigode.net>
License-File: LICENSE
Keywords: database,dbj,json
Classifier: Development Status :: 4 - Beta
Classifier: License :: OSI Approved :: MIT License
Classifier: Operating System :: OS Independent
Classifier: Programming Language :: Python :: 3
Requires-Python: >=3.8
